feincms/__init__.py
feincms/_internal.py
feincms/apps.py
feincms/contents.py
feincms/context_processors.py
feincms/default_settings.py
feincms/models.py
feincms/shortcuts.py
feincms/signals.py
feincms/translations.py
feincms/urls.py
feincms/admin/__init__.py
feincms/admin/filters.py
feincms/admin/item_editor.py
feincms/admin/tree_editor.py
feincms/content/__init__.py
feincms/content/application/__init__.py
feincms/content/application/models.py
feincms/content/contactform/__init__.py
feincms/content/contactform/models.py
feincms/content/file/__init__.py
feincms/content/file/models.py
feincms/content/filer/__init__.py
feincms/content/filer/models.py
feincms/content/image/__init__.py
feincms/content/image/models.py
feincms/content/medialibrary/__init__.py
feincms/content/medialibrary/models.py
feincms/content/raw/__init__.py
feincms/content/raw/models.py
feincms/content/richtext/__init__.py
feincms/content/richtext/models.py
feincms/content/section/__init__.py
feincms/content/section/models.py
feincms/content/template/__init__.py
feincms/content/template/models.py
feincms/content/video/__init__.py
feincms/content/video/models.py
feincms/contrib/__init__.py
feincms/contrib/fields.py
feincms/contrib/richtext.py
feincms/contrib/tagging.py
feincms/contrib/preview/__init__.py
feincms/contrib/preview/urls.py
feincms/contrib/preview/views.py
feincms/extensions/__init__.py
feincms/extensions/base.py
feincms/extensions/changedate.py
feincms/extensions/ct_tracker.py
feincms/extensions/datepublisher.py
feincms/extensions/featured.py
feincms/extensions/seo.py
feincms/extensions/translations.py
feincms/locale/ca/LC_MESSAGES/django.mo
feincms/locale/ca/LC_MESSAGES/django.po
feincms/locale/cs/LC_MESSAGES/django.mo
feincms/locale/cs/LC_MESSAGES/django.po
feincms/locale/de/LC_MESSAGES/django.mo
feincms/locale/de/LC_MESSAGES/django.po
feincms/locale/en/LC_MESSAGES/django.mo
feincms/locale/en/LC_MESSAGES/django.po
feincms/locale/es/LC_MESSAGES/django.mo
feincms-25.5.1.dist-info/licenses/LICENSE
feincms-25.5.1.dist-info/METADATA
feincms-25.5.1.dist-info/WHEEL
feincms-25.5.1.dist-info/top_level.txt
feincms-25.5.1.dist-info/RECORD
