Metadata-Version: 2.4
Name: FeinCMS
Version: 25.5.1
Summary: Django-based Page CMS and CMS building toolkit.
Home-page: http://github.com/feincms/feincms/
Author: Matthias Kestenholz
Author-email: mk@feinheit.ch
License: BSD-3-Clause
Platform: OS Independent
Classifier: Development Status :: 5 - Production/Stable
Classifier: Environment :: Web Environment
Classifier: Framework :: Django
Classifier: Intended Audience :: Developers
Classifier: License :: OSI Approved :: BSD License
Classifier: Operating System :: OS Independent
Classifier: Programming Language :: Python
Classifier: Programming Language :: Python :: 3
Classifier: Programming Language :: Python :: 3.8
Classifier: Programming Language :: Python :: 3.9
Classifier: Programming Language :: Python :: 3.10
Classifier: Programming Language :: Python :: 3.11
Classifier: Programming Language :: Python :: 3.12
Classifier: Programming Language :: Python :: Implementation :: CPython
Classifier: Topic :: Internet :: WWW/HTTP :: Dynamic Content
Classifier: Topic :: Software Development
Classifier: Topic :: Software Development :: Libraries :: Application Frameworks
Requires-Python: >=3.6
License-File: LICENSE
Requires-Dist: Django>=3.2
Requires-Dist: Pillow>=2.0.0
Requires-Dist: django-mptt>=0.7.1
Provides-Extra: tests
Requires-Dist: coverage; extra == "tests"
Dynamic: license-file
